main/launch.py
other/test.py
MonProjetKali-1.0.0.dist-info/LICENCE.txt
MonProjetKali-1.0.0.dist-info/METADATA
MonProjetKali-1.0.0.dist-info/WHEEL
MonProjetKali-1.0.0.dist-info/top_level.txt
MonProjetKali-1.0.0.dist-info/RECORD
